fileupload/__init__.py
fileupload/admin.py
fileupload/apps.py
fileupload/constants.py
fileupload/mixins.py
fileupload/models.py
fileupload/response.py
fileupload/serialize.py
fileupload/urls.py
fileupload/views.py
fileupload/api/__init__.py
fileupload/api/serializers.py
fileupload/locale/de/LC_MESSAGES/django.mo
fileupload/locale/de/LC_MESSAGES/django.po
fileupload/locale/es/LC_MESSAGES/django.mo
fileupload/locale/es/LC_MESSAGES/django.po
fileupload/migrations/0001_initial.py
fileupload/migrations/0002_auto_20171023_1418.py
fileupload/migrations/0003_auto_20171023_1422.py
fileupload/migrations/0004_auto_20171114_1511.py
fileupload/migrations/__init__.py
fileupload/templates/uploader_base.html
fileupload/templates/partials/_attachments_table.html
fileupload/templatetags/__init__.py
fileupload/templatetags/upload_file.py
fileupload/tests/__init__.py
fileupload/tests/conftest.py
fileupload/tests/test_settings.py
fileupload/tests/test_utils.py
fileupload/tests/tests.py
ai_django_fileupload-0.1.5.dist-info/LICENSE.md
ai_django_fileupload-0.1.5.dist-info/METADATA
ai_django_fileupload-0.1.5.dist-info/WHEEL
ai_django_fileupload-0.1.5.dist-info/top_level.txt
ai_django_fileupload-0.1.5.dist-info/RECORD
