Metadata-Version: 2.1
Name: ai-django-fileupload
Version: 0.1.5
Summary: Integrate jQuery fileupload
Home-page: https://gitlab.ambient-innovation.com/ai/ai-django-fileupload
Author: Ambient Innovation: GmbH
Author-email: hello@ambient-innovation.com
License: The MIT License (MIT)
Download-URL: https://gitlab.ambient-innovation.com/ai/ai-django-fileupload.git
Platform: UNKNOWN
License-File: LICENSE.md
Requires-Dist: pillow
